{
    "_id": "4lxprime",
    "created": "0001-01-01T00:00:00.000Z",
    "updated": "0001-01-01T00:00:00.000Z",
    "rvn": 0,
    "wipeNumber": 1,
    "accountId": "4lxprime",
    "profileId": "profile0",
    "version": "no_version",
    "items": {},
    "stats": {
        "templateId": "profile_v2",
        "attributes": {
            "mtx_purchase_history": {
                "purchases": []
            },
            "mission_alert_redemption_record": {
                "lastClaimTimesMap": {
                    "General": {
                        "missionAlertGUIDs": [
                            "",
                            "",
                            ""
                        ],
                        "lastClaimedTimes": []
                    },
                    "StormLow": {
                        "missionAlertGUIDs": [],
                        "lastClaimedTimes": []
                    },
                    "Halloween": {
                        "missionAlertGUIDs": [],
                        "lastClaimedTimes": []
                    },
                    "Horde": {
                        "missionAlertGUIDs": [],
                        "lastClaimedTimes": []
                    },
                    "Storm": {
                        "missionAlertGUIDs": [],
                        "lastClaimedTimes": []
                    }
                },
                "oldestClaimIndexForCategory": [
                    0,
                    0,
                    0,
                    0,
                    0
                ]
            },
            "twitch": {},
            "client_settings": {
                "pinnedQuestInstances": []
            },
            "level": 1,
            "named_counters": {
                "SubGameSelectCount_Campaign": {
                    "current_count": 0,
                    "last_incremented_time": "2022-09-15T21:38:24.350Z"
                },
                "SubGameSelectCount_Athena": {
                    "current_count": 0,
                    "last_incremented_time": "2022-12-18T12:37:13.822Z"
                }
            },
            "default_hero_squad_id": "",
            "collection_book": {
                "pages": [],
                "maxBookXpLevelAchieved": 0
            },
            "quest_manager": {
                "dailyLoginInterval": "2022-09-15T19:17:02.785Z",
                "dailyQuestRerolls": 1
            },
            "bans": {},
            "gameplay_stats": [
                {
                    "statName": "zonescompleted",
                    "statValue": 1
                }
            ],
            "inventory_limit_bonus": 100000,
            "current_mtx_platform": "Epic",
            "weekly_purchases": {},
            "daily_purchases": {
                "lastInterval": "2017-08-29T00:00:00.000Z",
                "purchaseList": {
                    "1F6B613D4B7BAD47D8A93CAEED2C4996": 1
                }
            },
            "mode_loadouts": [
                {
                    "loadoutName": "Default",
                    "selectedGadgets": [
                        "",
                        ""
                    ]
                }
            ],
            "in_app_purchases": {
                "receipts": [
                    "EPIC:0aba47abf15143f18370dbc70b910b14",
                    "EPIC:ee397e98af0042159fec830aea1224d5"
                ],
                "fulfillmentCounts": {
                    "0A6CB5B346A149F31A4C3FBDF4BBC198": 3,
                    "DEF6D31D416227E7D73F65B27288ED6F": 1,
                    "82ADCC874CFC2D47927208BAE871CF2B": 1,
                    "F0033207441AC38CD704718B91B2C8EF": 1
                }
            },
            "daily_rewards": {
                "nextDefaultReward": 1,
                "totalDaysLoggedIn": 1,
                "lastClaimDate": "2022-09-15T00:00:00.000Z",
                "additionalSchedules": {
                    "founderspackdailyrewardtoken": {
                        "rewardsClaimed": 1,
                        "claimedToday": true
                    }
                }
            },
            "monthly_purchases": {},
            "xp": 1,
            "homebase": {
                "townName": "Nocturno Town",
                "bannerIconId": "OT10Banner",
                "bannerColorId": "DefaultColor15",
                "flagPattern": -1,
                "flagColor": -1
            },
            "packs_granted": 0
        }
    },
    "commandRevision": 0
}